mdt/__init__.py
mdt/command.py
mdt/config.py
mdt/console.py
mdt/devices.py
mdt/discoverer.py
mdt/files.py
mdt/keys.py
mdt/main.py
mdt/shell.py
mdt/sshclient.py
mendel_development_tool-1.5.2.data/data/share/man/man1/mdt.1
mendel_development_tool-1.5.2.dist-info/DESCRIPTION.rst
mendel_development_tool-1.5.2.dist-info/METADATA
mendel_development_tool-1.5.2.dist-info/RECORD
mendel_development_tool-1.5.2.dist-info/WHEEL
mendel_development_tool-1.5.2.dist-info/entry_points.txt
mendel_development_tool-1.5.2.dist-info/metadata.json
mendel_development_tool-1.5.2.dist-info/top_level.txt
