Metadata-Version: 2.0
Name: mendel-development-tool
Version: 1.5.2
Summary: A command-line tool to manage Mendel Linux embedded systems
Home-page: https://coral.googlesource.com/mdt.git
Author: Mendel Linux Software Team
Author-email: coral-support@google.com
License: Apache 2
Keywords: embedded development
Platform: UNKNOWN
Classifier: Development Status :: 4 - Beta
Classifier: Intended Audience :: Developers
Classifier: Topic :: Software Development
Classifier: Topic :: Utilities
Classifier: License :: OSI Approved :: Apache Software License
Classifier: Operating System :: POSIX
Classifier: Programming Language :: Python :: 3
Requires-Python: >=3.5.0
Requires-Dist: paramiko (>=2.0.0)
Requires-Dist: zeroconf (>=0.27.0)
